extopen.py
extopen-0.1.1.dist-info/DESCRIPTION.rst
extopen-0.1.1.dist-info/METADATA
extopen-0.1.1.dist-info/RECORD
extopen-0.1.1.dist-info/WHEEL
extopen-0.1.1.dist-info/metadata.json
extopen-0.1.1.dist-info/top_level.txt
extopen-0.1.1.dist-info/zip-safe
